mdeq/__init__.py
mdeq/_block_threading.py
mdeq/_click_options.py
mdeq/adjacent.py
mdeq/bootstrap.py
mdeq/control.py
mdeq/convergence.py
mdeq/eop.py
mdeq/jsd.py
mdeq/model.py
mdeq/numeric.py
mdeq/stationary_pi.py
mdeq/toe.py
mdeq/utils.py
mdeq-2025.6.30.dist-info/entry_points.txt
mdeq-2025.6.30.dist-info/licenses/LICENSE
mdeq-2025.6.30.dist-info/WHEEL
mdeq-2025.6.30.dist-info/METADATA
mdeq-2025.6.30.dist-info/RECORD
