Metadata-Version: 2.4
Name: mdeq
Version: 2025.6.30
Summary: mdeq: mutation disequilibrium analysis tools.
Keywords: biology,genomics,statistics,phylogeny,evolution,bioinformatics
Author-email: Katherine Caley <katherine.caley@anu.edu.au>, Gavin Huttley <Gavin.Huttley@anu.edu.au>
Requires-Python: >=3.10,<3.14
Classifier: Development Status :: 5 - Production/Stable
Classifier: Intended Audience :: Science/Research
Classifier: License :: OSI Approved :: BSD License
Classifier: Topic :: Scientific/Engineering :: Bio-Informatics
Classifier: Topic :: Software Development :: Libraries :: Python Modules
Classifier: Operating System :: OS Independent
Classifier: Programming Language :: Python :: 3.10
Classifier: Programming Language :: Python :: 3.11
Classifier: Programming Language :: Python :: 3.12
Classifier: Programming Language :: Python :: 3.13
License-File: LICENSE
Requires-Dist: cogent3>=2025.7.10a5
Requires-Dist: click
Requires-Dist: numpy
Requires-Dist: scipy
Requires-Dist: scitrack
Requires-Dist: rich
Requires-Dist: trogon
Requires-Dist: cogapp ; extra == "dev"
Requires-Dist: docformatter ; extra == "dev"
Requires-Dist: mdeq[test] ; extra == "dev"
Requires-Dist: ruff==0.12.8 ; extra == "dev"
Requires-Dist: pytest ; extra == "test"
Requires-Dist: pytest-cov ; extra == "test"
Requires-Dist: pytest-xdist ; extra == "test"
Requires-Dist: nox ; extra == "test"
Provides-Extra: dev
Provides-Extra: test
